<DOMSymbolItem xmlns:xsi="http://www.w3.org/2001/XMLSchema-instance" xmlns="http://ns.adobe.com/xfl/2008/" name="images/MRI/hemispheres/right_hemisphere" itemID="4f62f72d-0000074c" linkageExportForAS="true" linkageClassName="right_hemisphere" lastModified="1331886644">
  <timeline>
    <DOMTimeline name="right_hemisphere" currentFrame="3">
      <layers>
        <DOMLayer name="Layer 1" color="#4FFF4F" current="true" isSelected="true">
          <frames>
            <DOMFrame index="0" keyMode="9728">
              <elements>
                <DOMBitmapInstance libraryItemName="images/MRI/hemispheres/right_normal.png"/>
              </elements>
            </DOMFrame>
            <DOMFrame index="1" keyMode="9728">
              <elements>
                <DOMBitmapInstance libraryItemName="images/MRI/hemispheres/right_white.png"/>
              </elements>
            </DOMFrame>
            <DOMFrame index="2" keyMode="9728">
              <elements>
                <DOMBitmapInstance libraryItemName="images/MRI/hemispheres/right_red.png"/>
              </elements>
            </DOMFrame>
            <DOMFrame index="3" keyMode="9728">
              <elements>
                <DOMBitmapInstance libraryItemName="images/MRI/hemispheres/right_green.png"/>
              </elements>
            </DOMFrame>
          </frames>
        </DOMLayer>
      </layers>
    </DOMTimeline>
  </timeline>
</DOMSymbolItem>